<powerpagecomponent powerpagecomponentid="9eb42d50-43ed-0e64-5cf6-d5a39735d379">
  <content>{
  "disablepagevalidation": false,
  "displayimageonly": false,
  "displayorder": 1,
  "displaypagechildlinks": false,
  "openinnewwindow": false,
  "pageid": "2fe25596-d771-fb08-c1a6-b0d9ee808b5f",
  "publishingstateid": "e007803a-e299-ee11-be37-0022483c04c3",
  "robotsfollowlink": true,
  "weblinksetid": "dcac7a40-e299-ee11-be37-0022483c04c3"
}</content>
  <iscustomizable>1</iscustomizable>
  <name>reference</name>
  <powerpagecomponenttype>5</powerpagecomponenttype>
  <powerpagesiteid>
    <powerpagesiteid>27ad7a40-e299-ee11-be37-0022483c04c3</powerpagesiteid>
  </powerpagesiteid>
  <statecode>0</statecode>
  <statuscode>1</statuscode>
</powerpagecomponent>